splitfxm/__init__.py
splitfxm/bc.py
splitfxm/boundary.py
splitfxm/cell.py
splitfxm/constants.py
splitfxm/derivatives.c
splitfxm/derivatives.cpython-39-darwin.so
splitfxm/derivatives.pyx
splitfxm/domain.py
splitfxm/error.py
splitfxm/flux.c
splitfxm/flux.cpython-39-darwin.so
splitfxm/flux.pyx
splitfxm/initialize.py
splitfxm/model.py
splitfxm/refine.py
splitfxm/schemes.py
splitfxm/simhelper.py
splitfxm/simulation.py
splitfxm/system.py
splitfxm/visualize.py
splitfxm/equations/__init__.py
splitfxm/equations/fd_transport.py
splitfxm/equations/fv_transport.py
splitfxm/models/__init__.py
splitfxm/models/advection_diffusion.py
splitfxm-0.5.2.dist-info/LICENSE.md
splitfxm-0.5.2.dist-info/METADATA
splitfxm-0.5.2.dist-info/WHEEL
splitfxm-0.5.2.dist-info/top_level.txt
splitfxm-0.5.2.dist-info/RECORD
