Metadata-Version: 2.1
Name: splitfxm
Version: 0.5.2
Summary: 1D Finite-Difference/Volume Split Newton Solver
Home-page: https://github.com/gpavanb1/SplitFXM
Author: gpavanb1
Author-email: gpavanb@gmail.com
License: CC BY-NC 4.0 for non-commercial use, commercial license available
Project-URL: Bug Reports, https://github.com/gpavanb1/SplitFXM/issues
Project-URL: Source, https://github.com/gpavanb1/SplitFXM/
Keywords: amr newton python finite-difference armijo optimization pseudotransient splitting
Platform: UNKNOWN
Classifier: Topic :: Scientific/Engineering :: Mathematics
Classifier: License :: Other/Proprietary License
Classifier: Programming Language :: Python :: 3
Classifier: Programming Language :: Python :: 3 :: Only
Requires-Dist: numpy
Requires-Dist: numdifftools
Requires-Dist: matplotlib
Requires-Dist: splitnewton
